jiama/cli.py
jiama/client.py
jiama/constant.py
jiama/manage.py
jiama/rmq.py
jiama/server.py
jiama/util.py
jiama-0.8.1.dist-info/LICENSE
jiama-0.8.1.dist-info/METADATA
jiama-0.8.1.dist-info/WHEEL
jiama-0.8.1.dist-info/entry_points.txt
jiama-0.8.1.dist-info/top_level.txt
jiama-0.8.1.dist-info/RECORD
