Metadata-Version: 2.1
Name: jiama
Version: 0.8.1
Summary: An aio RPC framework based on RabbitMQ.
Author-email: Li zhigang <imlzg@126.com>
License: MIT License
Project-URL: Homepage, https://github.com/liangshanpo/jiama
Project-URL: Bug Tracker, https://github.com/liangshanpo/jiama/issues
Keywords: asyncio,rpc,rabbitmq
Classifier: Development Status :: 5 - Production/Stable
Classifier: Intended Audience :: Developers
Classifier: Topic :: Communications
Classifier: License :: OSI Approved :: MIT License
Classifier: Framework :: AsyncIO
Classifier: Operating System :: OS Independent
Classifier: Programming Language :: Python
Classifier: Programming Language :: Python :: 3 :: Only
Classifier: Programming Language :: Python :: 3.10
Classifier: Programming Language :: Python :: 3.11
Requires-Python: >=3.10
License-File: LICENSE
Requires-Dist: aio-pika
Requires-Dist: click
Requires-Dist: yujian
Requires-Dist: tomli
Requires-Dist: loguru
